{
  "project": [
    {
      "fname": "R.seshu",
      "email": "seshu123@gmail.com",
      "uname": "seshu",
      "password": "Seshu@123",
      "repassword": "Seshu@123",
      "id": 1
    },
    {
      "fname": "vijay",
      "email": "vijay@gmail.com",
      "uname": "kumar",
      "password": "vijay",
      "repassword": "vijay",
      "id": 2
    },
    {
      "fname": "vijay",
      "email": "kumar@gmail.com",
      "uname": "vijju",
      "password": "vijay",
      "repassword": "vijay",
      "id": 3
    },
    {
      "fname": "vijay",
      "email": "vijay@gmail.com",
      "uname": "kumar",
      "password": "vijay",
      "repassword": "vijay",
      "id": 4
    },
    {
      "fname": "gaddammadhukiranreddy",
      "email": "kirana@143",
      "uname": "gaddam",
      "password": "Kiran@143",
      "repassword": "Kiran@143",
      "id": 5
    }
  ]
}